MANIFEST.in
README.rst
pyproject.toml
requirements.txt
setup.py
signals_utils/__init__.py
signals_utils.egg-info/PKG-INFO
signals_utils.egg-info/SOURCES.txt
signals_utils.egg-info/dependency_links.txt
signals_utils.egg-info/requires.txt
signals_utils.egg-info/top_level.txt
signals_utils/commons/__init__.py
signals_utils/commons/exceptions.py
signals_utils/signals/__init__.py
signals_utils/signals/mongo/__init__.py
signals_utils/signals/mongo/connector.py
signals_utils/signals/mongo/decorator.py
signals_utils/signals/mongo/signals.py
tests/__init__.py
tests/signals/__init__.py
tests/signals/mongo/__init__.py
tests/signals/mongo/tests_unit.py