Metadata-Version: 1.0
Name: signals-utils
Version: 1.14.0
Summary: Mongo signals utils for the curator core project
Home-page: https://github.com/usnistgov/signals_utils
Author: NIST IT Lab
Author-email: itl_inquiries@nist.gov
License: UNKNOWN
Platform: UNKNOWN
